stitch/__init__.py
stitch/_frontend.py
stitch/_version.py
stitch/stitch.py
stitch/labextension/build_log.json
stitch/labextension/package.json
stitch/labextension/static/lib_index_js.6f923342a378078276c3.js
stitch/labextension/static/lib_index_js.6f923342a378078276c3.js.map
stitch/labextension/static/lib_plugin_js.ea5504c9afb02f8ab321.js
stitch/labextension/static/lib_plugin_js.ea5504c9afb02f8ab321.js.map
stitch/labextension/static/lib_widget_js.95d2bcb5bd8752e1e16a.js
stitch/labextension/static/lib_widget_js.95d2bcb5bd8752e1e16a.js.map
stitch/labextension/static/remoteEntry.a690fb54d7ba2e44a651.js
stitch/labextension/static/remoteEntry.a690fb54d7ba2e44a651.js.map
stitch/labextension/static/style.js
stitch/nbextension/extension.js
stitch/nbextension/index.js
stitch/nbextension/index.js.map
stitch/tests/__init__.py
stitch/tests/conftest.py
stitch/tests/test_example.py
stitch/tests/test_nbextension_path.py
guidance_stitch-0.1.5.data/data/share/jupyter/nbextensions/stitch/extension.js
guidance_stitch-0.1.5.data/data/share/jupyter/nbextensions/stitch/index.js
guidance_stitch-0.1.5.data/data/share/jupyter/nbextensions/stitch/index.js.map
guidance_stitch-0.1.5.data/data/etc/jupyter/nbconfig/notebook.d/stitch.json
guidance_stitch-0.1.5.data/data/share/jupyter/labextensions/@guidance-ai/stitch/build_log.json
guidance_stitch-0.1.5.data/data/share/jupyter/labextensions/@guidance-ai/stitch/package.json
guidance_stitch-0.1.5.data/data/share/jupyter/labextensions/@guidance-ai/stitch/static/lib_index_js.6f923342a378078276c3.js
guidance_stitch-0.1.5.data/data/share/jupyter/labextensions/@guidance-ai/stitch/static/lib_index_js.6f923342a378078276c3.js.map
guidance_stitch-0.1.5.data/data/share/jupyter/labextensions/@guidance-ai/stitch/static/lib_plugin_js.ea5504c9afb02f8ab321.js
guidance_stitch-0.1.5.data/data/share/jupyter/labextensions/@guidance-ai/stitch/static/lib_plugin_js.ea5504c9afb02f8ab321.js.map
guidance_stitch-0.1.5.dist-info/METADATA
guidance_stitch-0.1.5.dist-info/WHEEL
guidance_stitch-0.1.5.dist-info/licenses/LICENSE.txt
guidance_stitch-0.1.5.dist-info/RECORD
